aixblock_core/.coveragerc
aixblock_core/__init__.py
aixblock_core/annotation_template/__init__.py
aixblock_core/annotation_template/api.py
aixblock_core/annotation_template/functions.py
aixblock_core/annotation_template/migrations/0001_initial.py
aixblock_core/annotation_template/migrations/0002_auto_20240123_0617.py
aixblock_core/annotation_template/migrations/0003_auto_20240201_0123.py
aixblock_core/annotation_template/migrations/0004_auto_20240214_1254.py
aixblock_core/annotation_template/migrations/0005_auto_20240226_1437.py
aixblock_core/annotation_template/migrations/0006_auto_20240416_9122.py
aixblock_core/annotation_template/migrations/0007_auto_20240416_2302.py
aixblock_core/annotation_template/migrations/0008_add_catalog_key_field.py
aixblock_core/annotation_template/migrations/0009_add_catalog_key.py
aixblock_core/annotation_template/migrations/0010_add_deleted.py
aixblock_core/annotation_template/migrations/__init__.py
aixblock_core/annotation_template/models.py
aixblock_core/annotation_template/serializers.py
aixblock_core/annotation_template/urls.py
aixblock_core/annotation_templates/.DS_Store
aixblock_core/annotation_templates/CONTRIBUTING.md
aixblock_core/annotation_templates/audio-speech-processing/automatic-speech-recognition/config.xml
aixblock_core/annotation_templates/audio-speech-processing/automatic-speech-recognition/config.yml
aixblock_core/annotation_templates/audio-speech-processing/automatic-speech-recognition/sample.json
aixblock_core/annotation_templates/audio-speech-processing/automatic-speech-recognition-using-segments/config.xml
aixblock_core/annotation_templates/audio-speech-processing/automatic-speech-recognition-using-segments/config.yml
aixblock_core/annotation_templates/audio-speech-processing/automatic-speech-recognition-using-segments/sample.json
aixblock_core/annotation_templates/audio-speech-processing/intent-classification/config.xml
aixblock_core-0.0.8.dist-info/METADATA
aixblock_core-0.0.8.dist-info/WHEEL
aixblock_core-0.0.8.dist-info/entry_points.txt
aixblock_core-0.0.8.dist-info/RECORD
