Metadata-Version: 2.1
Name: aixblock_core
Version: 0.0.8
Summary: 
Author: Tony Shark
Author-email: tony@aixblock.io
Requires-Python: >=3.10,<4.0
Classifier: Programming Language :: Python :: 3
Classifier: Programming Language :: Python :: 3.10
Classifier: Programming Language :: Python :: 3.11
